ml_git/__init__.py
ml_git/_metadata.py
ml_git/admin.py
ml_git/api.py
ml_git/config.py
ml_git/constants.py
ml_git/error_handler.py
ml_git/git_client.py
ml_git/log.py
ml_git/main.py
ml_git/manifest.py
ml_git/metadata.py
ml_git/ml_git_message.py
ml_git/pool.py
ml_git/refs.py
ml_git/repository.py
ml_git/sample.py
ml_git/spec.py
ml_git/tag.py
ml_git/utils.py
ml_git/version.info
ml_git/version.py
ml_git/commands/__init__.py
ml_git/commands/custom_options.py
ml_git/commands/custom_types.py
ml_git/commands/descriptor.py
ml_git/commands/entity.py
ml_git/commands/general.py
ml_git/commands/help_msg.py
ml_git/commands/prompt_msg.py
ml_git/commands/remote.py
ml_git/commands/repository.py
ml_git/commands/storage.py
ml_git/commands/utils.py
ml_git/commands/wizard.py
ml_git/file_system/__init__.py
ml_git/file_system/cache.py
ml_git/file_system/hashfs.py
ml_git/file_system/index.py
ml_git/file_system/local.py
ml_git/file_system/objects.py
ml_git/plugin_interface/__init__.py
ml_git/plugin_interface/data_plugin_constants.py
ml_git/plugin_interface/plugin_especialization.py
ml_git/relationship/__init__.py
ml_git/relationship/entity_manager.py
ml_git/relationship/github_manager.py
ml_git/relationship/local_entity_manager.py
ml_git/relationship/utils.py
ml_git/relationship/models/__init__.py
ml_git/relationship/models/config.py
ml_git/relationship/models/entity.py
ml_git/relationship/models/entity_version_relationships.py
ml_git/relationship/models/linked_entity.py
ml_git/relationship/models/metadata.py
ml_git/relationship/models/spec_version.py
ml_git/relationship/models/storage.py
ml_git/storages/__init__.py
ml_git/storages/azure_storage.py
ml_git/storages/google_drive_storage.py
ml_git/storages/multihash_storage.py
ml_git/storages/s3_storage.py
ml_git/storages/sftp_storage.py
ml_git/storages/storage.py
ml_git/storages/store_utils.py
tests/__init__.py
tests/integration/__init__.py
tests/integration/commands.py
tests/integration/conftest.py
tests/integration/helper.py
ml_git-2.9.9.dist-info/LICENSE.md
ml_git-2.9.9.dist-info/METADATA
ml_git-2.9.9.dist-info/WHEEL
ml_git-2.9.9.dist-info/entry_points.txt
ml_git-2.9.9.dist-info/top_level.txt
ml_git-2.9.9.dist-info/zip-safe
ml_git-2.9.9.dist-info/RECORD
