Metadata-Version: 2.1
Name: ml-git
Version: 2.9.9
Summary: ML-Git: version control for ML artefacts
Home-page: https://github.com/HPInc/ml-git
Author: Sebastien Tandel
License: GNU General Public License v2.0
Project-URL: Bug Tracker, https://github.com/HPInc/ml-git/issues
Keywords: version control,cloud storage,machine learning,datasets,labels,models
Platform: Any
Classifier: Development Status :: 4 - Beta
Classifier: Operating System :: OS Independent
Classifier: Programming Language :: Python
Classifier: Topic :: Software Development :: Libraries :: Python Modules
License-File: LICENSE.md
Requires-Dist: azure-core (==1.3.0)
Requires-Dist: azure-storage-blob (==12.0.0)
Requires-Dist: backcall (==0.2.0)
Requires-Dist: base58 (==1.0.3)
Requires-Dist: bcrypt (==3.2.0)
Requires-Dist: boto3 (==1.9.164)
Requires-Dist: botocore (==1.12.172)
Requires-Dist: cachetools (==4.2.2)
Requires-Dist: certifi (==2021.5.30)
Requires-Dist: cffi (==1.14.6)
Requires-Dist: charset-normalizer (==2.0.5)
Requires-Dist: click (==7.0)
Requires-Dist: click-completion (==0.5.2)
Requires-Dist: click-didyoumean (==0.0.3)
Requires-Dist: click-plugins (==1.1.1)
Requires-Dist: colorama (==0.4.1)
Requires-Dist: cryptography (==3.4.8)
Requires-Dist: cursor (==1.3.4)
Requires-Dist: decorator (==4.4.2)
Requires-Dist: deprecated (==1.2.13)
Requires-Dist: docutils (==0.17.1)
Requires-Dist: funcy (==1.15)
Requires-Dist: gitdb (==4.0.7)
Requires-Dist: gitpython (==3.1.0)
Requires-Dist: google-api-core (==2.0.1)
Requires-Dist: google-api-python-client (==2.21.0)
Requires-Dist: google-auth (==2.1.0)
Requires-Dist: google-auth-httplib2 (==0.1.0)
Requires-Dist: googleapis-common-protos (==1.53.0)
Requires-Dist: halo (==0.0.29)
Requires-Dist: httplib2 (==0.19.1)
Requires-Dist: humanize (==3.1.0)
Requires-Dist: idna (==3.2)
Requires-Dist: importlib-metadata (==4.8.1)
Requires-Dist: ipython (==7.16.1)
Requires-Dist: ipython-genutils (==0.2.0)
Requires-Dist: isodate (==0.6.0)
Requires-Dist: jedi (==0.18.0)
Requires-Dist: jinja2 (==3.0.1)
Requires-Dist: jmespath (==0.10.0)
Requires-Dist: jsonpickle (==2.0.0)
Requires-Dist: log-symbols (==0.0.14)
Requires-Dist: markupsafe (==2.0.1)
Requires-Dist: mock (==4.0.2)
Requires-Dist: morphys (==1.0)
Requires-Dist: msrest (==0.6.21)
Requires-Dist: networkx (==2.5.1)
Requires-Dist: oauth2client (==4.1.3)
Requires-Dist: oauthlib (==3.1.1)
Requires-Dist: paramiko (==2.7.2)
Requires-Dist: parso (==0.8.2)
Requires-Dist: pexpect (==4.8.0)
Requires-Dist: pickleshare (==0.7.5)
Requires-Dist: prettytable (==2.0.0)
Requires-Dist: prompt-toolkit (==3.0.19)
Requires-Dist: protobuf (==3.17.3)
Requires-Dist: ptyprocess (==0.7.0)
Requires-Dist: py-cid (==0.2.1)
Requires-Dist: py-multibase (==1.0.3)
Requires-Dist: py-multicodec (==0.1.3)
Requires-Dist: py-multihash (==0.2.3)
Requires-Dist: pyasn1 (==0.4.8)
Requires-Dist: pyasn1-modules (==0.2.8)
Requires-Dist: pycparser (==2.20)
Requires-Dist: pydot (==1.4.2)
Requires-Dist: pydrive2 (==1.7.3)
Requires-Dist: pygithub (==1.55)
Requires-Dist: pygments (==2.10.0)
Requires-Dist: pyjwt (==2.1.0)
Requires-Dist: pynacl (==1.4.0)
Requires-Dist: pyopenssl (==20.0.1)
Requires-Dist: pyparsing (==2.4.7)
Requires-Dist: python-baseconv (==1.2.2)
Requires-Dist: python-dateutil (==2.8.2)
Requires-Dist: pyvis (==0.1.9)
Requires-Dist: pyyaml (==5.4.1)
Requires-Dist: requests (==2.26.0)
Requires-Dist: requests-oauthlib (==1.3.0)
Requires-Dist: rsa (==4.7.2)
Requires-Dist: ruamel.yaml (==0.16.10)
Requires-Dist: ruamel.yaml.clib (==0.2.6)
Requires-Dist: s3transfer (==0.2.1)
Requires-Dist: shellingham (==1.5.0)
Requires-Dist: six (==1.16.0)
Requires-Dist: smmap (==4.0.0)
Requires-Dist: spinners (==0.0.24)
Requires-Dist: termcolor (==1.1.0)
Requires-Dist: toml (==0.10.0)
Requires-Dist: tqdm (==4.31.1)
Requires-Dist: traitlets (==4.3.3)
Requires-Dist: typing-extensions (==3.10.0.2)
Requires-Dist: uritemplate (==3.0.1)
Requires-Dist: urllib3 (==1.25.11)
Requires-Dist: varint (==1.0.2)
Requires-Dist: wcwidth (==0.2.5)
Requires-Dist: wrapt (==1.12.1)
Requires-Dist: zipp (==3.5.0)
